[{"games": 1.0, "region": "OCE", "patch": "5.11", "y": 7.5508443034435277, "champ": 11.0, "tier": "DIAMOND", "x": -0.47805360401818375}, {"games": 1.0, "region": "OCE", "patch": "5.11", "y": 9.4482417062896182, "champ": 11.0, "tier": "DIAMOND", "x": -1.8681430410797442}, {"games": 1.0, "region": "OCE", "patch": "5.11", "y": 6.4859180292907901, "champ": 11.0, "tier": "DIAMOND", "x": -2.3763754548868792}, {"games": 1.0, "region": "OCE", "patch": "5.11", "y": 9.2192721987589792, "champ": 11.0, "tier": "DIAMOND", "x": -1.7703317788634845}, {"games": 1.0, "region": "OCE", "patch": "5.11", "y": 6.4657832530478041, "champ": 11.0, "tier": "DIAMOND", "x": -1.2221758633093938}, {"games": 1.0, "region": "OCE", "patch": "5.11", "y": 1.9042839296377811, "champ": 11.0, "tier": "DIAMOND", "x": -4.2484206624726166}, {"games": 1.0, "region": "OCE", "patch": "5.11", "y": 1.5259638595653238, "champ": 11.0, "tier": "DIAMOND", "x": -2.7278770146637603}, {"games": 1.0, "region": "OCE", "patch": "5.11", "y": 3.0780859834350864, "champ": 11.0, "tier": "DIAMOND", "x": -4.0791102474131602}, {"games": 1.0, "region": "OCE", "patch": "5.11", "y": 0.69993222446964465, "champ": 11.0, "tier": "DIAMOND", "x": -5.2931090866686716}, {"games": 1.0, "region": "OCE", "patch": "5.11", "y": 2.4429893642502063, "champ": 11.0, "tier": "DIAMOND", "x": -4.7154032943368422}, {"games": 1.0, "region": "OCE", "patch": "5.11", "y": -0.24637705913711816, "champ": 11.0, "tier": "DIAMOND", "x": -7.0386765145137833}, {"games": 1.0, "region": "OCE", "patch": "5.11", "y": -0.43184652500678933, "champ": 11.0, "tier": "DIAMOND", "x": -5.1703432731681529}, {"games": 1.0, "region": "OCE", "patch": "5.11", "y": -0.83797363666103131, "champ": 11.0, "tier": "DIAMOND", "x": -5.9044475823080944}, {"games": 1.0, "region": "OCE", "patch": "5.11", "y": -1.2320655151890463, "champ": 11.0, "tier": "DIAMOND", "x": -5.1877457338296855}, {"games": 1.0, "region": "OCE", "patch": "5.11", "y": 7.9973897753396175, "champ": 11.0, "tier": "DIAMOND", "x": -2.0362564531651457}]