[{"games": 5.0, "region": "OCE", "patch": "5.14", "y": 2.6943691245269594, "champ": 131.0, "tier": "GOLD", "x": 5.4210096058386723}, {"games": 4.0, "region": "OCE", "patch": "5.14", "y": 5.1085728275779019, "champ": 131.0, "tier": "GOLD", "x": 6.9789337130770006}, {"games": 4.0, "region": "OCE", "patch": "5.14", "y": -1.5393544482655583, "champ": 131.0, "tier": "GOLD", "x": 4.8522176715246754}, {"games": 3.0, "region": "OCE", "patch": "5.14", "y": 3.2264575734992214, "champ": 131.0, "tier": "GOLD", "x": 7.4648688931712659}, {"games": 3.0, "region": "OCE", "patch": "5.14", "y": 0.71293933694648826, "champ": 131.0, "tier": "GOLD", "x": 8.049341414412666}, {"games": 3.0, "region": "OCE", "patch": "5.14", "y": -1.3027844754725493, "champ": 131.0, "tier": "GOLD", "x": 4.7146898882360597}, {"games": 3.0, "region": "OCE", "patch": "5.14", "y": -7.9554471383586964, "champ": 131.0, "tier": "GOLD", "x": -1.8035633279459384}, {"games": 2.0, "region": "OCE", "patch": "5.14", "y": 4.3319186529304918, "champ": 131.0, "tier": "GOLD", "x": 7.9029623286278898}, {"games": 2.0, "region": "OCE", "patch": "5.14", "y": 0.67242470770537199, "champ": 131.0, "tier": "GOLD", "x": 7.1086374654993687}, {"games": 2.0, "region": "OCE", "patch": "5.14", "y": 1.0102812536011714, "champ": 131.0, "tier": "GOLD", "x": 9.3228695544939963}, {"games": 2.0, "region": "OCE", "patch": "5.14", "y": 1.996969059882193, "champ": 131.0, "tier": "GOLD", "x": 6.0345268529737179}, {"games": 2.0, "region": "OCE", "patch": "5.14", "y": 1.9177149498795505, "champ": 131.0, "tier": "GOLD", "x": 6.3450382213895615}, {"games": 2.0, "region": "OCE", "patch": "5.14", "y": 4.18645644236513, "champ": 131.0, "tier": "GOLD", "x": 5.9061771829288396}, {"games": 2.0, "region": "OCE", "patch": "5.14", "y": -0.70810064216318325, "champ": 131.0, "tier": "GOLD", "x": 7.2617461683987194}, {"games": 2.0, "region": "OCE", "patch": "5.14", "y": 2.0796248677184455, "champ": 131.0, "tier": "GOLD", "x": 4.7058385857398983}, {"games": 2.0, "region": "OCE", "patch": "5.14", "y": -1.2420125316108752, "champ": 131.0, "tier": "GOLD", "x": 6.1257458116060057}, {"games": 2.0, "region": "OCE", "patch": "5.14", "y": -4.1243978396679228, "champ": 131.0, "tier": "GOLD", "x": -1.2692161864380926}, {"games": 1.0, "region": "OCE", "patch": "5.14", "y": 7.4906462085727537, "champ": 131.0, "tier": "GOLD", "x": 7.9596515304134714}, {"games": 1.0, "region": "OCE", "patch": "5.14", "y": 6.4387502275771773, "champ": 131.0, "tier": "GOLD", "x": 9.1033009258168303}, {"games": 1.0, "region": "OCE", "patch": "5.14", "y": 5.3752424417396369, "champ": 131.0, "tier": "GOLD", "x": 10.993217052794556}, {"games": 1.0, "region": "OCE", "patch": "5.14", "y": 0.9495093097394971, "champ": 131.0, "tier": "GOLD", "x": 7.9118136311240503}, {"games": 1.0, "region": "OCE", "patch": "5.14", "y": 4.3335865535268798, "champ": 131.0, "tier": "GOLD", "x": 4.2175314018081531}, {"games": 1.0, "region": "OCE", "patch": "5.14", "y": 4.2540826843455859, "champ": 131.0, "tier": "GOLD", "x": 9.7636025604709076}, {"games": 1.0, "region": "OCE", "patch": "5.14", "y": 5.6716462738809135, "champ": 131.0, "tier": "GOLD", "x": 7.7782146487989987}, {"games": 1.0, "region": "OCE", "patch": "5.14", "y": 6.7260619324822848, "champ": 131.0, "tier": "GOLD", "x": 11.292771695930103}, {"games": 1.0, "region": "OCE", "patch": "5.14", "y": 6.9996433872195993, "champ": 131.0, "tier": "GOLD", "x": 5.6662305296286419}, {"games": 1.0, "region": "OCE", "patch": "5.14", "y": 4.5484282022243523, "champ": 131.0, "tier": "GOLD", "x": 9.5973198054031599}, {"games": 1.0, "region": "OCE", "patch": "5.14", "y": 5.0295293953237463, "champ": 131.0, "tier": "GOLD", "x": 2.1180580338180843}, {"games": 1.0, "region": "OCE", "patch": "5.14", "y": 2.9983395550976075, "champ": 131.0, "tier": "GOLD", "x": 6.7967720147060362}, {"games": 1.0, "region": "OCE", "patch": "5.14", "y": -2.4301294188783973, "champ": 131.0, "tier": "GOLD", "x": 7.0163406433832023}, {"games": 1.0, "region": "OCE", "patch": "5.14", "y": -2.1097261764900912, "champ": 131.0, "tier": "GOLD", "x": 6.0843091593622418}, {"games": 1.0, "region": "OCE", "patch": "5.14", "y": -4.2165577511367758, "champ": 131.0, "tier": "GOLD", "x": 4.8839705621733014}, {"games": 1.0, "region": "OCE", "patch": "5.14", "y": -7.8355370671207796, "champ": 131.0, "tier": "GOLD", "x": 5.0303496479580785}, {"games": 1.0, "region": "OCE", "patch": "5.14", "y": 1.6103428214752926, "champ": 131.0, "tier": "GOLD", "x": 5.9874527113401737}, {"games": 1.0, "region": "OCE", "patch": "5.14", "y": -0.1098625147644916, "champ": 131.0, "tier": "GOLD", "x": 4.8341882557847775}, {"games": 1.0, "region": "OCE", "patch": "5.14", "y": -6.1158043752268814, "champ": 131.0, "tier": "GOLD", "x": 2.4493407292658871}, {"games": 1.0, "region": "OCE", "patch": "5.14", "y": -7.5946375776070187, "champ": 131.0, "tier": "GOLD", "x": 1.9475237301373254}, {"games": 1.0, "region": "OCE", "patch": "5.14", "y": 3.1070826164982814, "champ": 131.0, "tier": "GOLD", "x": 11.439150781714879}, {"games": 1.0, "region": "OCE", "patch": "5.14", "y": -4.1355284926545437, "champ": 131.0, "tier": "GOLD", "x": 6.7653784599998961}, {"games": 1.0, "region": "OCE", "patch": "5.14", "y": 5.7032566608872672, "champ": 131.0, "tier": "GOLD", "x": 9.5259899932396603}, {"games": 1.0, "region": "OCE", "patch": "5.14", "y": 9.0148638484670123, "champ": 131.0, "tier": "GOLD", "x": 9.0220253974054962}, {"games": 1.0, "region": "OCE", "patch": "5.14", "y": 6.4904628995905309, "champ": 131.0, "tier": "GOLD", "x": 4.4582610114264778}, {"games": 1.0, "region": "OCE", "patch": "5.14", "y": 1.662055493488648, "champ": 131.0, "tier": "GOLD", "x": 1.3424127969498212}, {"games": 1.0, "region": "OCE", "patch": "5.14", "y": -0.5561943100815594, "champ": 131.0, "tier": "GOLD", "x": 0.58968729825697874}, {"games": 1.0, "region": "OCE", "patch": "5.14", "y": 0.39669090180079047, "champ": 131.0, "tier": "GOLD", "x": 1.6633289950872197}, {"games": 1.0, "region": "OCE", "patch": "5.14", "y": -1.0821423005793478, "champ": 131.0, "tier": "GOLD", "x": 1.161511995958658}, {"games": 1.0, "region": "OCE", "patch": "5.14", "y": 3.5863948744910088, "champ": 131.0, "tier": "GOLD", "x": 9.2415940260826623}, {"games": 1.0, "region": "OCE", "patch": "5.14", "y": -1.544089835308246, "champ": 131.0, "tier": "GOLD", "x": 0.46068049689500201}, {"games": 1.0, "region": "OCE", "patch": "5.14", "y": -3.5297140063585561, "champ": 131.0, "tier": "GOLD", "x": 1.2778400937245666}, {"games": 1.0, "region": "OCE", "patch": "5.14", "y": -4.8472450684965978, "champ": 131.0, "tier": "GOLD", "x": 0.15902043097532026}, {"games": 1.0, "region": "OCE", "patch": "5.14", "y": -7.8946751944970224, "champ": 131.0, "tier": "GOLD", "x": -0.39250740457599287}, {"games": 1.0, "region": "OCE", "patch": "5.14", "y": -6.4205644402427202, "champ": 131.0, "tier": "GOLD", "x": 6.3319404186281316}, {"games": 1.0, "region": "OCE", "patch": "5.14", "y": 2.8471467845476433, "champ": 131.0, "tier": "GOLD", "x": 5.7638443809287514}, {"games": 1.0, "region": "OCE", "patch": "5.14", "y": -1.8392212153561323, "champ": 131.0, "tier": "GOLD", "x": 6.7034888672945332}, {"games": 1.0, "region": "OCE", "patch": "5.14", "y": 5.1700225468229988, "champ": 131.0, "tier": "GOLD", "x": 7.8350205000935915}, {"games": 1.0, "region": "OCE", "patch": "5.14", "y": 5.9466767214704088, "champ": 131.0, "tier": "GOLD", "x": 6.9109918845427032}, {"games": 1.0, "region": "OCE", "patch": "5.14", "y": -0.70125055437305162, "champ": 131.0, "tier": "GOLD", "x": 4.7842758429903771}, {"games": 1.0, "region": "OCE", "patch": "5.14", "y": -0.85889315568445523, "champ": 131.0, "tier": "GOLD", "x": -0.47609503908112094}]