[{"games": 1.0, "region": "LAS", "patch": "5.14", "y": 9.2793696614572045, "champ": 29.0, "tier": "DIAMOND", "x": -1.0185386257747422}, {"games": 1.0, "region": "LAS", "patch": "5.14", "y": 8.7835143904356041, "champ": 29.0, "tier": "DIAMOND", "x": -2.4834646915248033}, {"games": 1.0, "region": "LAS", "patch": "5.14", "y": 1.1060593361238857, "champ": 29.0, "tier": "DIAMOND", "x": -4.559004777528731}, {"games": 1.0, "region": "LAS", "patch": "5.14", "y": 2.4429893642502063, "champ": 29.0, "tier": "DIAMOND", "x": -4.7154032943368422}]